<?xml version="1.0" encoding="utf-8"?>
<modsCollection xmlns:xlink="http://www.w3.org/1999/xlink" xmlns:xsi="http://www.w3.org/2001/XMLSchema-instance">
  <mods version="3.5">
    <titleInfo>
      <title>Effect of grafting and modified atmosphere packaging (MAP) on melon quality parameters during storage</title>
      <subTitle />
    </titleInfo>
    <name type="personal">
      <namePart type="family">Christakou</namePart>
      <namePart type="given">Evangelia C.</namePart>
      <role>
        <roleTerm type="text" authority="marcrelator">author</roleTerm>
      </role>
      <affiliation>University of Thessaly, School of Agricultural Sciences, Department of Agriculture Crop Production &amp; Agricultural Environment, Fytoko Street, 38446 Nea Ionia Magnesias, Volos, Hellas (Greece).</affiliation>
    </name>
    <name type="personal">
      <namePart type="family">Arvanitoyannis</namePart>
      <namePart type="given">Ioannis S.</namePart>
      <role>
        <roleTerm type="text" authority="marcrelator">author</roleTerm>
      </role>
      <affiliation>University of Thessaly, School of Agricultural Sciences, Department of Agriculture Crop Production &amp; Agricultural Environment, Fytoko Street, 38446 Nea Ionia Magnesias, Volos, Hellas (Greece).</affiliation>
    </name>
    <name type="personal">
      <namePart type="family">Khah</namePart>
      <namePart type="given">Ebrahim M.</namePart>
      <role>
        <roleTerm type="text" authority="marcrelator">author</roleTerm>
      </role>
      <affiliation>University of Thessaly, School of Agricultural Sciences, Department of Agriculture Crop Production &amp; Agricultural Environment, Fytoko Street, 38446 Nea Ionia Magnesias, Volos, Hellas (Greece).</affiliation>
    </name>
    <name type="personal">
      <namePart type="family">Bletsos</namePart>
      <namePart type="given">Fotios</namePart>
      <role>
        <roleTerm type="text" authority="marcrelator">author</roleTerm>
      </role>
      <affiliation>National Agricultural Research Foundation (N.AG.RE.F), Agricultural Research Centre of Macedonia and Thrace, P.O. Box 60458, 57001 Thermi-Thessaloniki, Greece.</affiliation>
    </name>
    <typeOfResource>text</typeOfResource>
    <genre>article</genre>
    <originInfo>
      <dateIssued encoding="w3cdtf" keyDate="yes"></dateIssued>
    </originInfo>
    <language>
      <languageTerm type="code" authority="iso639-2b">eng</languageTerm>
      <languageTerm type="text">English</languageTerm>
    </language>
    <physicalDescription>
      <form authority="marcform">electronic</form>
    </physicalDescription>
    <abstract>The physicochemical (pH, mechanical firmness and vitamin C) and sensory parameters of grafted and ungrafted melon plants were studied in relation to storage time (up to 21 days at 10°C). Melon seedlings of cultivar ‘Galia’ were grafted on commercial hybrids ‘Mamouth’ and ‘9075’ rootstocks to avoid the soil-borne disease caused by Fusarium oxysporum f. sp. melonis. The fruits were stored under modified atmosphere (30% CO2, 70% N2) at 10°C. Vitamin C was not affected by grafting and modified atmosphere but decreased during storage. pH was not affected neither by grafting nor by MAP. Flesh firmness decreased during storage but was not considerably affected by grafting or modified atmosphere. Sensory analysis did not reveal any statistical differences between fruits from grafted and ungrafted plants. Fruit quality decreased during storage, but modified atmosphere helped in better maintaining of the fruits in comparison with air.</abstract>
    <relatedItem type="host">
      <titleInfo>
        <title>Journal of Food, Agriculture and Environment</title>
      </titleInfo>
      <originInfo>
        <publisher>WFL Publisher</publisher>
      </originInfo>
      <identifier type="issn">1459-0263</identifier>
      <part>
        <detail type="volume">
          <number>3</number>
          <caption>v.</caption>
        </detail>
        <detail type="issue">
          <number>1</number>
          <caption>no.</caption>
        </detail>
        <extent unit="pages">
          <start>145</start>
          <end>152</end>
        </extent>
        <date>2005</date>
      </part>
    </relatedItem>
    <identifier type="uri">http://world-food.net/download/journals/2005-issue_1/a8.pdf</identifier>
  </mods>
</modsCollection>