<?xml version="1.0" encoding="utf-8"?>
<modsCollection xmlns:xlink="http://www.w3.org/1999/xlink" xmlns:xsi="http://www.w3.org/2001/XMLSchema-instance">
  <mods version="3.5">
    <titleInfo>
      <title>The effect of NaCl priming on cucumber seedling growth under salinity stress</title>
      <subTitle />
    </titleInfo>
    <name type="personal">
      <namePart type="family">Esmaielpour</namePart>
      <namePart type="given">B.</namePart>
      <role>
        <roleTerm type="text" authority="marcrelator">author</roleTerm>
      </role>
      <affiliation>Department of Horticulture, Faculty of Agriculture, University of Tabriz, Tabriz, Iran.</affiliation>
    </name>
    <name type="personal">
      <namePart type="family">Ghassemi-Golezani</namePart>
      <namePart type="given">K.</namePart>
      <role>
        <roleTerm type="text" authority="marcrelator">author</roleTerm>
      </role>
      <affiliation>Department of Agronomy and Plant Breeding, Faculty of Agriculture, University of Tabriz, Tabriz, Iran.</affiliation>
    </name>
    <name type="personal">
      <namePart type="family">Khoei</namePart>
      <namePart type="given">F. Rahimzadeh</namePart>
      <role>
        <roleTerm type="text" authority="marcrelator">author</roleTerm>
      </role>
      <affiliation>Department of Agronomy and Plant Breeding, Faculty of Agriculture, University of Tabriz, Tabriz, Iran.</affiliation>
    </name>
    <name type="personal">
      <namePart type="family">Gregoorian</namePart>
      <namePart type="given">V.</namePart>
      <role>
        <roleTerm type="text" authority="marcrelator">author</roleTerm>
      </role>
      <affiliation>Department of Horticulture, Faculty of Agriculture, University of Tabriz, Tabriz, Iran.</affiliation>
    </name>
    <name type="personal">
      <namePart type="family">Toorchi</namePart>
      <namePart type="given">M.</namePart>
      <role>
        <roleTerm type="text" authority="marcrelator">author</roleTerm>
      </role>
      <affiliation>Department of Agronomy and Plant Breeding, Faculty of Agriculture, University of Tabriz, Tabriz, Iran.</affiliation>
    </name>
    <typeOfResource>text</typeOfResource>
    <genre>article</genre>
    <originInfo>
      <dateIssued encoding="w3cdtf" keyDate="yes"></dateIssued>
    </originInfo>
    <language>
      <languageTerm type="code" authority="iso639-2b">eng</languageTerm>
      <languageTerm type="text">English</languageTerm>
    </language>
    <physicalDescription>
      <form authority="marcform">electronic</form>
    </physicalDescription>
    <abstract>Seeds of two Iranian cucumber cultivars, Basmenj and Varamin, were primed (P) with 15 dS m-1 NaCl solution for 36 h at 20°C. Non-primed (NP) and primed (P) seeds were sown in trays containing perlite. The trays were placed in an unheated greenhouse and irrigated with different levels of NaCl solution (0.3 (control), 2.5, 5, 9 and 13 dS m-1 ) for a period of 4 weeks. Total emergence, emergence rate, radicle length and dry weight of seedlings derived from P seeds were higher than NP seeds. NaCl priming increased uptake of K and Ca and accumulation of proline in cucumber seedlings. These results indicated that NaCl priming increased salt tolerance of cucumber seedlings by promoting K and Ca accumulation in addition to inducing osmoregulation by accumulation of proline.</abstract>
    <relatedItem type="host">
      <titleInfo>
        <title>Journal of Food, Agriculture and Environment</title>
      </titleInfo>
      <originInfo>
        <publisher>WFL Publisher</publisher>
      </originInfo>
      <identifier type="issn">1459-0263</identifier>
      <part>
        <detail type="volume">
          <number>4</number>
          <caption>v.</caption>
        </detail>
        <detail type="issue">
          <number>2</number>
          <caption>no.</caption>
        </detail>
        <extent unit="pages">
          <start>347</start>
          <end>349</end>
        </extent>
        <date>2006</date>
      </part>
    </relatedItem>
    <identifier type="uri">http://world-food.net/download/journals/2006-issue_2/e18.pdf</identifier>
  </mods>
</modsCollection>