<?xml version="1.0" encoding="utf-8"?>
<modsCollection xmlns:xlink="http://www.w3.org/1999/xlink" xmlns:xsi="http://www.w3.org/2001/XMLSchema-instance">
  <mods version="3.5">
    <titleInfo>
      <title>In vitro propagation and cryopreservation of Prunus avium using vitrification and encapsulation dehydration methods</title>
      <subTitle />
    </titleInfo>
    <name type="personal">
      <namePart type="family">Shatnawi</namePart>
      <namePart type="given">Mohamad A.</namePart>
      <role>
        <roleTerm type="text" authority="marcrelator">author</roleTerm>
      </role>
      <affiliation>Al-Balqa Applied University, Faculty of Agriculture Technology, Al-Salt 19117, Jordan.</affiliation>
    </name>
    <name type="personal">
      <namePart type="family">Shibli</namePart>
      <namePart type="given">Rida</namePart>
      <role>
        <roleTerm type="text" authority="marcrelator">author</roleTerm>
      </role>
      <affiliation>Jordan University of Science and Technology, Irbid, Jordan.</affiliation>
    </name>
    <name type="personal">
      <namePart type="family">Qrunfleh</namePart>
      <namePart type="given">Issam</namePart>
      <role>
        <roleTerm type="text" authority="marcrelator">author</roleTerm>
      </role>
      <affiliation>Al-Balqa Applied University, Faculty of Agriculture Technology, Al-Salt 19117, Jordan.</affiliation>
    </name>
    <name type="personal">
      <namePart type="family">Bataeineh</namePart>
      <namePart type="given">Khaled</namePart>
      <role>
        <roleTerm type="text" authority="marcrelator">author</roleTerm>
      </role>
      <affiliation>Department of Biological Science, Yarmouk University, Irbid, Jordan.</affiliation>
    </name>
    <name type="personal">
      <namePart type="family">Obeidat</namePart>
      <namePart type="given">Maher</namePart>
      <role>
        <roleTerm type="text" authority="marcrelator">author</roleTerm>
      </role>
      <affiliation>Al-Balqa Applied University, Faculty of Agriculture Technology, Al-Salt 19117, Jordan.</affiliation>
    </name>
    <typeOfResource>text</typeOfResource>
    <genre>article</genre>
    <originInfo>
      <dateIssued encoding="w3cdtf" keyDate="yes"></dateIssued>
    </originInfo>
    <language>
      <languageTerm type="code" authority="iso639-2b">eng</languageTerm>
      <languageTerm type="text">English</languageTerm>
    </language>
    <physicalDescription>
      <form authority="marcform">electronic</form>
    </physicalDescription>
    <abstract>The present study aims to develop a reliable method for in vitro micropropagation and long-term storage of shoot tips in Prunus avium using vitrification and encapsulation dehydration methods. For micropropagation, maximum number of shoots per explant was obtained on Murashige and Skoog (MS) medium supplemented with 1.0 mg/L BA (benzyl amino purine). Several pretreatments prior to cryogenic storage were conducted to enhance shoot tips recovery after cryostorage. Using vitrification method, two different preculture treatments were tested to enhance regrowth after both dehydration and cryopreservation. Further accumulation of sucrose and glycerol was tested. The highest regrowth using this method was (up to 77.8%) when shoot tips were exposed to 60 min PVS2 at 0ºC. Growth recovery of cryopreserved shoot tips using encapsulation dehydration was (up to 76.3%) obtained when encapsulated shoot tips were pregrown for 3 d in liquid medium containing 0.75 M sucrose, desiccated to 20-22% moisture content and immersed in liquid nitrogen. Recovery of whole plantlets from cryopreserved shoot tips took place directly without transitory callus formation. Both methods are promising techniques for in vitro propagation and germplasm preservation of P. avium shoot tips.</abstract>
    <relatedItem type="host">
      <titleInfo>
        <title>Journal of Food, Agriculture and Environment</title>
      </titleInfo>
      <originInfo>
        <publisher>WFL Publisher</publisher>
      </originInfo>
      <identifier type="issn">1459-0263</identifier>
      <part>
        <detail type="volume">
          <number>5</number>
          <caption>v.</caption>
        </detail>
        <detail type="issue">
          <number>2</number>
          <caption>no.</caption>
        </detail>
        <extent unit="pages">
          <start>204</start>
          <end>208</end>
        </extent>
        <date>2007</date>
      </part>
    </relatedItem>
    <identifier type="uri">http://world-food.net/download/journals/2007-issue_2/a20.pdf</identifier>
  </mods>
</modsCollection>